investpy/__init__.py
investpy/calculos.py
investpy/dados.py
investpy/visualizacao.py
investimentpy_vbrito-1.0.5.dist-info/METADATA
investimentpy_vbrito-1.0.5.dist-info/WHEEL
investimentpy_vbrito-1.0.5.dist-info/top_level.txt
investimentpy_vbrito-1.0.5.dist-info/RECORD
