Metadata-Version: 2.1
Name: investimentpy-vbrito
Version: 1.0.5
Summary: Uma biblioteca para análise de investimentos
Home-page: https://github.com/Valmisonds/investimentpy
Author: Valmison Brito
Author-email: valmisonbrito@gmail.com
License: MIT
